bandupy/__init__.py
bandupy/argparse_wrapper.py
bandupy/build.py
bandupy/constants.py
bandupy/defaults.py
bandupy/figs.py
bandupy/files.py
bandupy/lists.py
bandupy/orbital_contributions.py
bandupy/plot.py
bandupy/runners.py
bandupy/sysargv.py
bandupy/unfolding_density_op.py
bandupy/unfolding_path.py
bandupy/vasp.py
bandupy/version.py
bandupy/warnings_wrapper.py
bandupy/plot_gui/__init__.py
bandupy/plot_gui/main_window.py
bandupy-0.1.1.dist-info/LICENSE
bandupy-0.1.1.dist-info/METADATA
bandupy-0.1.1.dist-info/WHEEL
bandupy-0.1.1.dist-info/top_level.txt
bandupy-0.1.1.dist-info/RECORD
