Metadata-Version: 2.1
Name: bandupy
Version: 0.1.1
Summary: Python interfaceof the BandUP code
Home-page: https://www.ifm.liu.se/theomod/compphys/band-unfolding/
Author: Stepan S. Tsirkin
Author-email: stepan.tsirkin@uzh.ch
License: UNKNOWN
Platform: UNKNOWN
Classifier: Programming Language :: Python :: 3
Classifier: License :: OSI Approved :: GNU General Public License v3 (GPLv3)
Classifier: Operating System :: OS Independent
Requires-Dist: irrep (>=1.5.1)
Requires-Dist: matplotlib
Requires-Dist: numpy
Requires-Dist: scipy (>=1.0)
